{"is_source_file": true, "format": "Python", "description": "This file provides database connection handling for MongoDB within a backend application, including connection initialization, health check, and index setup for the 'devices' collection.", "external_files": ["pymongo", "config"], "external_methods": ["pymongo.MongoClient()", "pymongo.errors", "Settings.load_from_env()"], "published": ["get_db", "is_db_available", "ensure_indexes"], "classes": [], "methods": [{"name": "Optional[MongoClient] _get_client()", "description": "Initializes and returns a singleton MongoDB client, testing the connection with a ping.", "scope": "", "scopeKind": ""}, {"name": "get_db()", "description": "Returns the database handle or None if connection is unavailable.", "scope": "", "scopeKind": ""}, {"name": "Tuple[bool,Optional[str]] is_db_available()", "description": "Checks if the database is reachable by sending a ping command and returns a tuple indicating status and error message if any.", "scope": "", "scopeKind": ""}, {"name": "ensure_indexes()", "description": "Creates indexes on the 'devices' collection for fields 'ip_address', 'type', and 'status'.", "scope": "", "scopeKind": ""}], "calls": ["Settings.load_from_env", "MongoClient", "client.admin.command", "client.get_database", "db.get_collection", "devices.create_index"], "search-terms": ["MongoDB connection", "database health check", "index setup", "devices collection", "MongoClient singleton"], "state": 2, "file_id": 12, "knowledge_revision": 51, "git_revision": "428575291c2456e46daf2686525ea5d0a9fadc40", "revision_history": [{"30": ""}, {"51": "428575291c2456e46daf2686525ea5d0a9fadc40"}], "ctags": [{"_type": "tag", "name": "_client", "path": "/home/kavia/workspace/code-generation/containerized-network-management-6128-5252/BackendApplication/db.py", "pattern": "/^_client: Optional[MongoClient] = None$/", "language": "Python", "typeref": "typename:Optional[MongoClient]", "kind": "variable"}, {"_type": "tag", "name": "_get_client", "path": "/home/kavia/workspace/code-generation/containerized-network-management-6128-5252/BackendApplication/db.py", "pattern": "/^def _get_client() -> Optional[MongoClient]:$/", "language": "Python", "typeref": "typename:Optional[MongoClient]", "kind": "function", "signature": "()"}, {"_type": "tag", "name": "ensure_indexes", "path": "/home/kavia/workspace/code-generation/containerized-network-management-6128-5252/BackendApplication/db.py", "pattern": "/^def ensure_indexes():$/", "language": "Python", "kind": "function", "signature": "()"}, {"_type": "tag", "name": "get_db", "path": "/home/kavia/workspace/code-generation/containerized-network-management-6128-5252/BackendApplication/db.py", "pattern": "/^def get_db():$/", "language": "Python", "kind": "function", "signature": "()"}, {"_type": "tag", "name": "is_db_available", "path": "/home/kavia/workspace/code-generation/containerized-network-management-6128-5252/BackendApplication/db.py", "pattern": "/^def is_db_available() -> Tuple[bool, Optional[str]]:$/", "language": "Python", "typeref": "typename:Tuple[bool,Optional[str]]", "kind": "function", "signature": "()"}], "hash": "25750047809382964ef7e31f8338deaf", "format-version": 4, "code-base-name": "BackendApplication", "filename": "BackendApplication/db.py", "fields": [{"name": "Optional[MongoClient] _client", "scope": "", "scopeKind": "", "description": "unavailable"}]}